<?xml version="1.0" encoding="UTF-8"?>
<MTConnectStreams xmlns="urn:mtconnect.org:MTConnectStreams:1.3" xmlns:xsi="http://www.w3.org/2001/XMLSchema-instance" xsi:schemaLocation="urn:mtconnect.org:MTConnectStreams:1.3 http://www.mtconnect.org/schemas/MTConnectStreams_1.3.xsd">
    <Header creationTime="2025-07-03T11:46:22.963Z" sender="MTConnect Local Agent" instanceId="1" version="1.3.0" bufferSize="131072" firstSequence="1" lastSequence="8" nextSequence="9"/>
    <Streams>
        <DeviceStream name="STUDER DT-26" uuid="DT-26"><ComponentStream component="Device" name="DT-26" componentId=""><Events><AssetChanged dataItemId="_asset_chg" timestamp="2025-07-03T05:52:15.915Z" sequence="20" assetType="">UNAVAILABLE</AssetChanged><Availability dataItemId="avail" timestamp="2025-07-03T05:52:51.138Z" sequence="35">UNAVAILABLE</Availability></Events></ComponentStream><ComponentStream component="Rotary" name="A" componentId="a1"><Samples><Angle dataItemId="Aact" timestamp="2025-07-03T05:52:15.915Z" name="ALact" sequence="1">UNAVAILABLE</Angle><Load dataItemId="Aload" timestamp="2025-07-03T05:52:15.915Z" name="ALload" sequence="2">UNAVAILABLE</Load></Samples></ComponentStream><ComponentStream component="Rotary" name="B" componentId="b1"><Samples><Angle dataItemId="Bact" timestamp="2025-07-03T05:52:15.915Z" name="Bact" sequence="3">UNAVAILABLE</Angle><Load dataItemId="Bload" timestamp="2025-07-03T05:52:15.915Z" name="Bload" sequence="4">UNAVAILABLE</Load></Samples></ComponentStream><ComponentStream component="Rotary" name="C" componentId="c1"><Samples><Angle dataItemId="Cact" timestamp="2025-07-03T05:52:15.915Z" name="Cact" sequence="5">UNAVAILABLE</Angle><Load dataItemId="Cload" timestamp="2025-07-03T05:52:15.915Z" name="Cload" sequence="6">UNAVAILABLE</Load></Samples></ComponentStream><ComponentStream component="Controller" name="controller" componentId="cn1"><Events><EmergencyStop dataItemId="estop" timestamp="2025-07-03T05:52:15.915Z" sequence="23">UNAVAILABLE</EmergencyStop></Events><Condition><Unavailable dataItemId="system" timestamp="2025-07-03T05:52:15.915Z" sequence="32" type="SYSTEM"/></Condition></ComponentStream><ComponentStream component="Path" name="path" componentId="pth"><Samples><PathFeedrate dataItemId="fd1" timestamp="2025-07-03T05:52:15.915Z" name="feedrate" sequence="25">UNAVAILABLE</PathFeedrate><PathFeedrate dataItemId="fd2" timestamp="2025-07-03T05:52:15.915Z" name="Fovr" sequence="26" subType="OVERRIDE">UNAVAILABLE</PathFeedrate><FeedrateOverride dataItemId="fd3" timestamp="2025-07-03T05:52:15.915Z" name="Rovr" sequence="27" subType="RAPID">UNAVAILABLE</FeedrateOverride></Samples><Events><Block dataItemId="block" timestamp="2025-07-03T05:52:15.915Z" name="block" sequence="22">UNAVAILABLE</Block><Execution dataItemId="execution" timestamp="2025-07-03T05:52:15.915Z" name="exec" sequence="24">UNAVAILABLE</Execution><Line dataItemId="line" timestamp="2025-07-03T05:52:15.915Z" name="line" sequence="28">UNAVAILABLE</Line><ControllerMode dataItemId="mode" timestamp="2025-07-03T05:52:15.915Z" name="mode" sequence="29">UNAVAILABLE</ControllerMode><PartCount dataItemId="part_count" timestamp="2025-07-03T05:52:15.915Z" name="part_count" sequence="30">UNAVAILABLE</PartCount><Program dataItemId="program" timestamp="2025-07-03T05:52:15.915Z" name="program" sequence="31">UNAVAILABLE</Program><ToolId dataItemId="tool_id" timestamp="2025-07-03T05:52:15.915Z" name="ToolId" sequence="33">UNAVAILABLE</ToolId></Events></ComponentStream><ComponentStream component="Rotary" name="S0" componentId="s0"><Samples><SpindleSpeed dataItemId="SSovr" timestamp="2025-07-03T05:52:15.915Z" name="Sovr" sequence="11" subType="OVERRIDE">UNAVAILABLE</SpindleSpeed><SpindleSpeed dataItemId="Sspeed" timestamp="2025-07-03T05:52:15.915Z" name="Sspeed" sequence="13" subType="ACTUAL">UNAVAILABLE</SpindleSpeed><Load dataItemId="Sload" timestamp="2025-07-03T05:52:15.915Z" name="Sload" sequence="12" subType="ACTUAL">UNAVAILABLE</Load></Samples></ComponentStream><ComponentStream component="Rotary" name="S1" componentId="s1"><Samples><Load dataItemId="S1load" timestamp="2025-07-03T05:52:15.915Z" name="S1load" sequence="7" subType="ACTUAL">UNAVAILABLE</Load><SpindleSpeed dataItemId="S1speed" timestamp="2025-07-03T05:52:15.915Z" name="S1speed" sequence="8" subType="ACTUAL">UNAVAILABLE</SpindleSpeed></Samples></ComponentStream><ComponentStream component="Rotary" name="S2" componentId="s2"><Samples><Load dataItemId="S2load" timestamp="2025-07-03T05:52:15.915Z" name="S2load" sequence="9" subType="ACTUAL">UNAVAILABLE</Load><SpindleSpeed dataItemId="S2speed" timestamp="2025-07-03T05:52:15.915Z" name="S2speed" sequence="10" subType="ACTUAL">UNAVAILABLE</SpindleSpeed></Samples></ComponentStream><ComponentStream component="Linear" name="X" componentId="x1"><Samples><Position dataItemId="Xact" timestamp="2025-07-03T05:52:15.915Z" name="Xact" sequence="14">UNAVAILABLE</Position><Load dataItemId="Xload" timestamp="2025-07-03T05:52:15.915Z" name="Xload" sequence="15">UNAVAILABLE</Load></Samples></ComponentStream><ComponentStream component="Linear" name="Y" componentId="z1"><Samples><Position dataItemId="Yact" timestamp="2025-07-03T05:52:15.915Z" name="Yact" sequence="16">UNAVAILABLE</Position><Load dataItemId="Yload" timestamp="2025-07-03T05:52:15.915Z" name="Yload" sequence="17">UNAVAILABLE</Load></Samples></ComponentStream><ComponentStream component="Linear" name="Z" componentId="z1"><Samples><Position dataItemId="Zact" timestamp="2025-07-03T05:52:15.915Z" name="Zact" sequence="18">UNAVAILABLE</Position><Load dataItemId="Zload" timestamp="2025-07-03T05:52:15.915Z" name="Zload" sequence="19">UNAVAILABLE</Load></Samples></ComponentStream></DeviceStream>
<DeviceStream name="SR-10" uuid="SR-10"><ComponentStream component="Device" name="SR-10" componentId=""><Events><AssetChanged dataItemId="_asset_chg" timestamp="2025-07-03T05:52:15.872Z" sequence="20" assetType="">UNAVAILABLE</AssetChanged><Availability dataItemId="avail" timestamp="2025-07-03T05:52:15.951Z" sequence="34">AVAILABLE</Availability></Events></ComponentStream><ComponentStream component="Rotary" name="A" componentId="a1"><Samples><Angle dataItemId="Aact" timestamp="2025-07-03T05:52:15.872Z" name="ALact" sequence="1">UNAVAILABLE</Angle><Load dataItemId="Aload" timestamp="2025-07-03T05:52:15.872Z" name="ALload" sequence="2">UNAVAILABLE</Load></Samples></ComponentStream><ComponentStream component="Rotary" name="B" componentId="b1"><Samples><Angle dataItemId="Bact" timestamp="2025-07-03T05:52:15.872Z" name="Bact" sequence="3">UNAVAILABLE</Angle><Load dataItemId="Bload" timestamp="2025-07-03T05:52:15.872Z" name="Bload" sequence="4">UNAVAILABLE</Load></Samples></ComponentStream><ComponentStream component="Rotary" name="C" componentId="c1"><Samples><Angle dataItemId="Cact" timestamp="2025-07-03T11:46:03.217Z" name="Cact" sequence="312308">35</Angle><Load dataItemId="Cload" timestamp="2025-07-03T11:46:03.740Z" name="Cload" sequence="312319">0</Load></Samples></ComponentStream><ComponentStream component="Controller" name="controller" componentId="cn1"><Events><EmergencyStop dataItemId="estop" timestamp="2025-07-03T05:52:16.291Z" sequence="44">ARMED</EmergencyStop></Events><Condition><Normal dataItemId="system" timestamp="2025-07-03T05:52:15.951Z" sequence="35" type="SYSTEM"/></Condition></ComponentStream><ComponentStream component="Path" name="path" componentId="pth"><Samples>
        <ProcessTimer dataItemId="cycle_time_avg" timestamp="2025-07-03T11:46:13.833Z" name="CycleTime" sequence="48096" subType="AVERAGE" type="PROCESS_TIMER">30.07</ProcessTimer><PathFeedrate dataItemId="fd1" timestamp="2025-07-03T05:52:15.872Z" name="feedrate" sequence="25">UNAVAILABLE</PathFeedrate><PathFeedrate dataItemId="fd2" timestamp="2025-07-03T05:52:16.291Z" name="Fovr" sequence="37" subType="OVERRIDE">100</PathFeedrate><FeedrateOverride dataItemId="fd3" timestamp="2025-07-03T05:52:15.872Z" name="Rovr" sequence="27" subType="RAPID">UNAVAILABLE</FeedrateOverride><ProcessTimer dataItemId="cycle_time_avg" timestamp="2025-07-03T11:46:13.833Z" name="CycleTime" sequence="57230" subType="AVERAGE" type="PROCESS_TIMER">30.07</ProcessTimer></Samples><Events><Block dataItemId="block" timestamp="2025-07-03T11:46:21.981Z" name="block" sequence="312623">T0100(DGN 1402J)</Block><Execution dataItemId="execution" timestamp="2025-07-03T11:26:02.037Z" name="exec" sequence="290792">ACTIVE</Execution><Line dataItemId="line" timestamp="2025-07-03T10:50:36.132Z" name="line" sequence="268399">1111</Line><ControllerMode dataItemId="mode" timestamp="2025-07-03T05:52:16.291Z" name="mode" sequence="42">AUTOMATIC</ControllerMode><PartCount dataItemId="part_count" timestamp="2025-07-03T11:46:13.833Z" name="part_count" sequence="312461">1948</PartCount><Program dataItemId="program" timestamp="2025-07-03T11:46:21.981Z" name="program" sequence="268398">DGN 1402J</Program><ToolId dataItemId="tool_id" timestamp="2025-07-03T11:46:21.981Z" name="ToolId" sequence="312622">1</ToolId></Events></ComponentStream><ComponentStream component="Rotary" name="S0" componentId="s0"><Samples><SpindleSpeed dataItemId="SSovr" timestamp="2025-07-03T05:52:15.872Z" name="Sovr" sequence="11" subType="OVERRIDE">UNAVAILABLE</SpindleSpeed><SpindleSpeed dataItemId="Sspeed" timestamp="2025-07-03T05:52:15.872Z" name="Sspeed" sequence="13" subType="ACTUAL">UNAVAILABLE</SpindleSpeed><Load dataItemId="Sload" timestamp="2025-07-03T05:52:15.872Z" name="Sload" sequence="12" subType="ACTUAL">UNAVAILABLE</Load></Samples></ComponentStream><ComponentStream component="Rotary" name="S1" componentId="s1"><Samples><Load dataItemId="S1load" timestamp="2025-07-03T11:46:21.981Z" name="S1load" sequence="312631" subType="ACTUAL">32</Load><SpindleSpeed dataItemId="S1speed" timestamp="2025-07-03T11:46:21.981Z" name="S1speed" sequence="312630" subType="ACTUAL">1714</SpindleSpeed></Samples></ComponentStream><ComponentStream component="Rotary" name="S2" componentId="s2"><Samples><Load dataItemId="S2load" timestamp="2025-07-03T05:52:15.872Z" name="S2load" sequence="9" subType="ACTUAL">UNAVAILABLE</Load><SpindleSpeed dataItemId="S2speed" timestamp="2025-07-03T05:52:15.872Z" name="S2speed" sequence="10" subType="ACTUAL">UNAVAILABLE</SpindleSpeed></Samples></ComponentStream><ComponentStream component="Linear" name="X" componentId="x1"><Samples><Position dataItemId="Xact" timestamp="2025-07-03T11:46:21.981Z" name="Xact" sequence="312624">40</Position><Load dataItemId="Xload" timestamp="2025-07-03T11:46:21.981Z" name="Xload" sequence="312632">2</Load></Samples></ComponentStream><ComponentStream component="Linear" name="Y" componentId="z1"><Samples><Position dataItemId="Yact" timestamp="2025-07-03T11:46:21.981Z" name="Yact" sequence="312628">0</Position><Load dataItemId="Yload" timestamp="2025-07-03T11:46:21.981Z" name="Yload" sequence="312629">49</Load></Samples></ComponentStream><ComponentStream component="Linear" name="Z" componentId="z1"><Samples><Position dataItemId="Zact" timestamp="2025-07-03T11:46:21.981Z" name="Zact" sequence="312626">83.345</Position><Load dataItemId="Zload" timestamp="2025-07-03T11:46:21.981Z" name="Zload" sequence="312633">0</Load></Samples></ComponentStream></DeviceStream>
<DeviceStream name="SR-21" uuid="SR-21"><ComponentStream component="Device" name="SR-21" componentId=""><Events><AssetChanged dataItemId="_asset_chg" timestamp="2025-07-03T05:52:15.981Z" sequence="20" assetType="">UNAVAILABLE</AssetChanged><Availability dataItemId="avail" timestamp="2025-07-03T05:52:16.074Z" sequence="34">AVAILABLE</Availability></Events></ComponentStream><ComponentStream component="Rotary" name="A" componentId="a1"><Samples><Angle dataItemId="Aact" timestamp="2025-07-03T05:52:16.315Z" name="ALact" sequence="63">0</Angle><Load dataItemId="Aload" timestamp="2025-07-03T11:46:21.461Z" name="ALload" sequence="371841">1</Load></Samples></ComponentStream><ComponentStream component="Rotary" name="B" componentId="b1"><Samples><Angle dataItemId="Bact" timestamp="2025-07-03T05:52:15.981Z" name="Bact" sequence="3">UNAVAILABLE</Angle><Load dataItemId="Bload" timestamp="2025-07-03T05:52:15.981Z" name="Bload" sequence="4">UNAVAILABLE</Load></Samples></ComponentStream><ComponentStream component="Rotary" name="C" componentId="c1"><Samples><Angle dataItemId="Cact" timestamp="2025-07-03T05:52:16.315Z" name="Cact" sequence="65">0</Angle><Load dataItemId="Cload" timestamp="2025-07-03T05:52:16.315Z" name="Cload" sequence="66">0</Load></Samples></ComponentStream><ComponentStream component="Controller" name="controller" componentId="cn1"><Events><EmergencyStop dataItemId="estop" timestamp="2025-07-03T05:52:16.315Z" sequence="44">ARMED</EmergencyStop></Events><Condition><Normal dataItemId="system" timestamp="2025-07-03T08:54:53.149Z" sequence="187812" type="SYSTEM"/></Condition></ComponentStream><ComponentStream component="Path" name="path" componentId="pth"><Samples>
        <ProcessTimer dataItemId="cycle_time_avg" timestamp="2025-07-03T11:46:06.035Z" name="CycleTime" sequence="31532" subType="AVERAGE" type="PROCESS_TIMER">54.33</ProcessTimer><PathFeedrate dataItemId="fd1" timestamp="2025-07-03T05:52:15.981Z" name="feedrate" sequence="25">UNAVAILABLE</PathFeedrate><PathFeedrate dataItemId="fd2" timestamp="2025-07-03T05:52:16.315Z" name="Fovr" sequence="37" subType="OVERRIDE">100</PathFeedrate><FeedrateOverride dataItemId="fd3" timestamp="2025-07-03T05:52:15.981Z" name="Rovr" sequence="27" subType="RAPID">UNAVAILABLE</FeedrateOverride><ProcessTimer dataItemId="cycle_time_avg" timestamp="2025-07-03T11:46:06.035Z" name="CycleTime" sequence="45714" subType="AVERAGE" type="PROCESS_TIMER">54.33</ProcessTimer></Samples><Events><Block dataItemId="block" timestamp="2025-07-03T11:46:18.703Z" name="block" sequence="371782">G01 Z10.000 F0.05</Block><Execution dataItemId="execution" timestamp="2025-07-03T11:08:57.145Z" name="exec" sequence="330888">ACTIVE</Execution><Line dataItemId="line" timestamp="2025-07-03T11:46:06.035Z" name="line" sequence="371514">1111</Line><ControllerMode dataItemId="mode" timestamp="2025-07-03T08:56:12.004Z" name="mode" sequence="188169">AUTOMATIC</ControllerMode><PartCount dataItemId="part_count" timestamp="2025-07-03T11:46:06.035Z" name="part_count" sequence="371513">604140</PartCount><Program dataItemId="program" timestamp="2025-07-03T11:45:42.253Z" name="program" sequence="371163">72.72</Program><ToolId dataItemId="tool_id" timestamp="2025-07-03T11:46:18.318Z" name="ToolId" sequence="371770">14</ToolId></Events></ComponentStream><ComponentStream component="Rotary" name="S0" componentId="s0"><Samples><SpindleSpeed dataItemId="SSovr" timestamp="2025-07-03T05:52:15.981Z" name="Sovr" sequence="11" subType="OVERRIDE">UNAVAILABLE</SpindleSpeed><SpindleSpeed dataItemId="Sspeed" timestamp="2025-07-03T05:52:15.981Z" name="Sspeed" sequence="13" subType="ACTUAL">UNAVAILABLE</SpindleSpeed><Load dataItemId="Sload" timestamp="2025-07-03T05:52:15.981Z" name="Sload" sequence="12" subType="ACTUAL">UNAVAILABLE</Load></Samples></ComponentStream><ComponentStream component="Rotary" name="S1" componentId="s1"><Samples><Load dataItemId="S1load" timestamp="2025-07-03T11:46:20.286Z" name="S1load" sequence="371817" subType="ACTUAL">3</Load><SpindleSpeed dataItemId="S1speed" timestamp="2025-07-03T11:46:21.844Z" name="S1speed" sequence="371844" subType="ACTUAL">3000</SpindleSpeed></Samples></ComponentStream><ComponentStream component="Rotary" name="S2" componentId="s2"><Samples><Load dataItemId="S2load" timestamp="2025-07-03T05:52:15.981Z" name="S2load" sequence="9" subType="ACTUAL">UNAVAILABLE</Load><SpindleSpeed dataItemId="S2speed" timestamp="2025-07-03T05:52:15.981Z" name="S2speed" sequence="10" subType="ACTUAL">UNAVAILABLE</SpindleSpeed></Samples></ComponentStream><ComponentStream component="Linear" name="X" componentId="x1"><Samples><Position dataItemId="Xact" timestamp="2025-07-03T11:46:21.057Z" name="Xact" sequence="371831">336.748</Position><Load dataItemId="Xload" timestamp="2025-07-03T11:46:21.844Z" name="Xload" sequence="371845">4</Load></Samples></ComponentStream><ComponentStream component="Linear" name="Y" componentId="z1"><Samples><Position dataItemId="Yact" timestamp="2025-07-03T11:46:17.934Z" name="Yact" sequence="371763">-366.006</Position><Load dataItemId="Yload" timestamp="2025-07-03T11:46:19.901Z" name="Yload" sequence="371809">1</Load></Samples></ComponentStream><ComponentStream component="Linear" name="Z" componentId="z1"><Samples><Position dataItemId="Zact" timestamp="2025-07-03T11:46:22.626Z" name="Zact" sequence="371853">79.519</Position><Load dataItemId="Zload" timestamp="2025-07-03T11:46:22.626Z" name="Zload" sequence="371854">15</Load></Samples></ComponentStream></DeviceStream>
<DeviceStream name="SR-23" uuid="SR-23"><ComponentStream component="Device" name="SR-23" componentId=""><Events><AssetChanged dataItemId="_asset_chg" timestamp="2025-07-03T05:52:16.030Z" sequence="20" assetType="">UNAVAILABLE</AssetChanged><Availability dataItemId="avail" timestamp="2025-07-03T05:52:17.028Z" sequence="34">AVAILABLE</Availability></Events></ComponentStream><ComponentStream component="Rotary" name="A" componentId="a1"><Samples><Angle dataItemId="Aact" timestamp="2025-07-03T05:52:16.030Z" name="ALact" sequence="1">UNAVAILABLE</Angle><Load dataItemId="Aload" timestamp="2025-07-03T05:52:16.030Z" name="ALload" sequence="2">UNAVAILABLE</Load></Samples></ComponentStream><ComponentStream component="Rotary" name="B" componentId="b1"><Samples><Angle dataItemId="Bact" timestamp="2025-07-03T05:52:16.030Z" name="Bact" sequence="3">UNAVAILABLE</Angle><Load dataItemId="Bload" timestamp="2025-07-03T05:52:16.030Z" name="Bload" sequence="4">UNAVAILABLE</Load></Samples></ComponentStream><ComponentStream component="Rotary" name="C" componentId="c1"><Samples><Angle dataItemId="Cact" timestamp="2025-07-03T05:52:16.030Z" name="Cact" sequence="5">UNAVAILABLE</Angle><Load dataItemId="Cload" timestamp="2025-07-03T05:52:16.030Z" name="Cload" sequence="6">UNAVAILABLE</Load></Samples></ComponentStream><ComponentStream component="Controller" name="controller" componentId="cn1"><Events><EmergencyStop dataItemId="estop" timestamp="2025-07-03T05:52:17.251Z" sequence="42">ARMED</EmergencyStop></Events><Condition><Normal dataItemId="system" timestamp="2025-07-03T05:52:17.028Z" sequence="35" type="SYSTEM"/></Condition></ComponentStream><ComponentStream component="Path" name="path" componentId="pth"><Samples>
        <ProcessTimer dataItemId="cycle_time_avg" timestamp="2025-07-03T11:46:03.263Z" name="CycleTime" sequence="62339" subType="AVERAGE" type="PROCESS_TIMER">40.07</ProcessTimer><PathFeedrate dataItemId="fd1" timestamp="2025-07-03T05:52:16.030Z" name="feedrate" sequence="25">UNAVAILABLE</PathFeedrate><PathFeedrate dataItemId="fd2" timestamp="2025-07-03T05:52:17.251Z" name="Fovr" sequence="38" subType="OVERRIDE">100</PathFeedrate><FeedrateOverride dataItemId="fd3" timestamp="2025-07-03T05:52:16.030Z" name="Rovr" sequence="27" subType="RAPID">UNAVAILABLE</FeedrateOverride><ProcessTimer dataItemId="cycle_time_avg" timestamp="2025-07-03T11:46:03.263Z" name="CycleTime" sequence="30811" subType="AVERAGE" type="PROCESS_TIMER">40.07</ProcessTimer></Samples><Events><Block dataItemId="block" timestamp="2025-07-03T11:46:17.585Z" name="block" sequence="23837">G1Z10.4,C0.15F0.03</Block><Execution dataItemId="execution" timestamp="2025-07-03T05:52:17.251Z" name="exec" sequence="37">ACTIVE</Execution><Line dataItemId="line" timestamp="2025-07-03T11:39:37.000Z" name="line" sequence="23376">1111</Line><ControllerMode dataItemId="mode" timestamp="2025-07-03T05:52:17.251Z" name="mode" sequence="41">AUTOMATIC</ControllerMode><PartCount dataItemId="part_count" timestamp="2025-07-03T11:46:03.263Z" name="part_count" sequence="23810">132197</PartCount><Program dataItemId="program" timestamp="2025-07-03T05:52:16.030Z" name="program" sequence="31">UNAVAILABLE</Program><ToolId dataItemId="tool_id" timestamp="2025-07-03T05:52:16.030Z" name="ToolId" sequence="33">UNAVAILABLE</ToolId></Events></ComponentStream><ComponentStream component="Rotary" name="S0" componentId="s0"><Samples><SpindleSpeed dataItemId="SSovr" timestamp="2025-07-03T05:52:16.030Z" name="Sovr" sequence="11" subType="OVERRIDE">UNAVAILABLE</SpindleSpeed><SpindleSpeed dataItemId="Sspeed" timestamp="2025-07-03T05:52:16.030Z" name="Sspeed" sequence="13" subType="ACTUAL">UNAVAILABLE</SpindleSpeed><Load dataItemId="Sload" timestamp="2025-07-03T05:52:16.030Z" name="Sload" sequence="12" subType="ACTUAL">UNAVAILABLE</Load></Samples></ComponentStream><ComponentStream component="Rotary" name="S1" componentId="s1"><Samples><Load dataItemId="S1load" timestamp="2025-07-03T11:46:14.712Z" name="S1load" sequence="23834" subType="ACTUAL">1</Load><SpindleSpeed dataItemId="S1speed" timestamp="2025-07-03T11:46:17.585Z" name="S1speed" sequence="23838" subType="ACTUAL">2000</SpindleSpeed></Samples></ComponentStream><ComponentStream component="Rotary" name="S2" componentId="s2"><Samples><Load dataItemId="S2load" timestamp="2025-07-03T05:52:16.030Z" name="S2load" sequence="9" subType="ACTUAL">UNAVAILABLE</Load><SpindleSpeed dataItemId="S2speed" timestamp="2025-07-03T05:52:16.030Z" name="S2speed" sequence="10" subType="ACTUAL">UNAVAILABLE</SpindleSpeed></Samples></ComponentStream><ComponentStream component="Linear" name="X" componentId="x1"><Samples><Position dataItemId="Xact" timestamp="2025-07-03T05:52:16.030Z" name="Xact" sequence="14">UNAVAILABLE</Position><Load dataItemId="Xload" timestamp="2025-07-03T05:52:16.030Z" name="Xload" sequence="15">UNAVAILABLE</Load></Samples></ComponentStream><ComponentStream component="Linear" name="Y" componentId="z1"><Samples><Position dataItemId="Yact" timestamp="2025-07-03T05:52:16.030Z" name="Yact" sequence="16">UNAVAILABLE</Position><Load dataItemId="Yload" timestamp="2025-07-03T05:52:16.030Z" name="Yload" sequence="17">UNAVAILABLE</Load></Samples></ComponentStream><ComponentStream component="Linear" name="Z" componentId="z1"><Samples><Position dataItemId="Zact" timestamp="2025-07-03T05:52:16.030Z" name="Zact" sequence="18">UNAVAILABLE</Position><Load dataItemId="Zload" timestamp="2025-07-03T05:52:16.030Z" name="Zload" sequence="19">UNAVAILABLE</Load></Samples></ComponentStream></DeviceStream>
<DeviceStream name="SR-25" uuid="SR-25"><ComponentStream component="Device" name="SR-25" componentId=""><Events><AssetChanged dataItemId="_asset_chg" timestamp="2025-07-03T05:52:16.080Z" sequence="20" assetType="">UNAVAILABLE</AssetChanged><Availability dataItemId="avail" timestamp="2025-07-03T10:29:18.535Z" sequence="252">UNAVAILABLE</Availability></Events></ComponentStream><ComponentStream component="Rotary" name="A" componentId="a1"><Samples><Angle dataItemId="Aact" timestamp="2025-07-03T05:52:16.080Z" name="ALact" sequence="1">UNAVAILABLE</Angle><Load dataItemId="Aload" timestamp="2025-07-03T05:52:16.080Z" name="ALload" sequence="2">UNAVAILABLE</Load></Samples></ComponentStream><ComponentStream component="Rotary" name="B" componentId="b1"><Samples><Angle dataItemId="Bact" timestamp="2025-07-03T05:52:16.080Z" name="Bact" sequence="3">UNAVAILABLE</Angle><Load dataItemId="Bload" timestamp="2025-07-03T05:52:16.080Z" name="Bload" sequence="4">UNAVAILABLE</Load></Samples></ComponentStream><ComponentStream component="Rotary" name="C" componentId="c1"><Samples><Angle dataItemId="Cact" timestamp="2025-07-03T05:52:16.080Z" name="Cact" sequence="5">UNAVAILABLE</Angle><Load dataItemId="Cload" timestamp="2025-07-03T05:52:16.080Z" name="Cload" sequence="6">UNAVAILABLE</Load></Samples></ComponentStream><ComponentStream component="Controller" name="controller" componentId="cn1"><Events><EmergencyStop dataItemId="estop" timestamp="2025-07-03T10:29:18.535Z" sequence="259">UNAVAILABLE</EmergencyStop></Events><Condition><Unavailable dataItemId="system" timestamp="2025-07-03T10:29:29.830Z" sequence="263" type="SYSTEM"/></Condition></ComponentStream><ComponentStream component="Path" name="path" componentId="pth"><Samples><PathFeedrate dataItemId="fd1" timestamp="2025-07-03T05:52:16.080Z" name="feedrate" sequence="25">UNAVAILABLE</PathFeedrate><PathFeedrate dataItemId="fd2" timestamp="2025-07-03T10:29:18.535Z" name="Fovr" sequence="255" subType="OVERRIDE">UNAVAILABLE</PathFeedrate><FeedrateOverride dataItemId="fd3" timestamp="2025-07-03T05:52:16.080Z" name="Rovr" sequence="27" subType="RAPID">UNAVAILABLE</FeedrateOverride></Samples><Events><Block dataItemId="block" timestamp="2025-07-03T10:29:18.535Z" name="block" sequence="257">UNAVAILABLE</Block><Execution dataItemId="execution" timestamp="2025-07-03T10:29:30.841Z" name="exec" sequence="264">UNAVAILABLE</Execution><Line dataItemId="line" timestamp="2025-07-03T10:29:18.535Z" name="line" sequence="256">UNAVAILABLE</Line><ControllerMode dataItemId="mode" timestamp="2025-07-03T10:29:18.535Z" name="mode" sequence="258">UNAVAILABLE</ControllerMode><PartCount dataItemId="part_count" timestamp="2025-07-03T10:29:18.535Z" name="part_count" sequence="253">UNAVAILABLE</PartCount><Program dataItemId="program" timestamp="2025-07-03T06:53:49.257Z" name="program" sequence="55">UNAVAILABLE</Program><ToolId dataItemId="tool_id" timestamp="2025-07-03T06:53:49.257Z" name="ToolId" sequence="54">UNAVAILABLE</ToolId></Events></ComponentStream><ComponentStream component="Rotary" name="S0" componentId="s0"><Samples><SpindleSpeed dataItemId="SSovr" timestamp="2025-07-03T05:52:16.080Z" name="Sovr" sequence="11" subType="OVERRIDE">UNAVAILABLE</SpindleSpeed><SpindleSpeed dataItemId="Sspeed" timestamp="2025-07-03T05:52:16.080Z" name="Sspeed" sequence="13" subType="ACTUAL">UNAVAILABLE</SpindleSpeed><Load dataItemId="Sload" timestamp="2025-07-03T05:52:16.080Z" name="Sload" sequence="12" subType="ACTUAL">UNAVAILABLE</Load></Samples></ComponentStream><ComponentStream component="Rotary" name="S1" componentId="s1"><Samples><Load dataItemId="S1load" timestamp="2025-07-03T10:29:18.535Z" name="S1load" sequence="261" subType="ACTUAL">UNAVAILABLE</Load><SpindleSpeed dataItemId="S1speed" timestamp="2025-07-03T10:29:18.535Z" name="S1speed" sequence="260" subType="ACTUAL">UNAVAILABLE</SpindleSpeed></Samples></ComponentStream><ComponentStream component="Rotary" name="S2" componentId="s2"><Samples><Load dataItemId="S2load" timestamp="2025-07-03T05:52:16.080Z" name="S2load" sequence="9" subType="ACTUAL">UNAVAILABLE</Load><SpindleSpeed dataItemId="S2speed" timestamp="2025-07-03T05:52:16.080Z" name="S2speed" sequence="10" subType="ACTUAL">UNAVAILABLE</SpindleSpeed></Samples></ComponentStream><ComponentStream component="Linear" name="X" componentId="x1"><Samples><Position dataItemId="Xact" timestamp="2025-07-03T05:52:16.080Z" name="Xact" sequence="14">UNAVAILABLE</Position><Load dataItemId="Xload" timestamp="2025-07-03T05:52:16.080Z" name="Xload" sequence="15">UNAVAILABLE</Load></Samples></ComponentStream><ComponentStream component="Linear" name="Y" componentId="z1"><Samples><Position dataItemId="Yact" timestamp="2025-07-03T05:52:16.080Z" name="Yact" sequence="16">UNAVAILABLE</Position><Load dataItemId="Yload" timestamp="2025-07-03T05:52:16.080Z" name="Yload" sequence="17">UNAVAILABLE</Load></Samples></ComponentStream><ComponentStream component="Linear" name="Z" componentId="z1"><Samples><Position dataItemId="Zact" timestamp="2025-07-03T05:52:16.080Z" name="Zact" sequence="18">UNAVAILABLE</Position><Load dataItemId="Zload" timestamp="2025-07-03T05:52:16.080Z" name="Zload" sequence="19">UNAVAILABLE</Load></Samples></ComponentStream></DeviceStream>
<DeviceStream name="SR-26" uuid="SR-26"><ComponentStream component="Device" name="SR-26" componentId=""><Events><AssetChanged dataItemId="_asset_chg" timestamp="2025-07-03T05:52:15.722Z" sequence="20" assetType="">UNAVAILABLE</AssetChanged><Availability dataItemId="avail" timestamp="2025-07-03T10:31:11.060Z" sequence="44335">AVAILABLE</Availability></Events></ComponentStream><ComponentStream component="Rotary" name="A" componentId="a1"><Samples><Angle dataItemId="Aact" timestamp="2025-07-03T05:52:15.722Z" name="ALact" sequence="1">UNAVAILABLE</Angle><Load dataItemId="Aload" timestamp="2025-07-03T05:52:15.722Z" name="ALload" sequence="2">UNAVAILABLE</Load></Samples></ComponentStream><ComponentStream component="Rotary" name="B" componentId="b1"><Samples><Angle dataItemId="Bact" timestamp="2025-07-03T05:52:15.722Z" name="Bact" sequence="3">UNAVAILABLE</Angle><Load dataItemId="Bload" timestamp="2025-07-03T05:52:15.722Z" name="Bload" sequence="4">UNAVAILABLE</Load></Samples></ComponentStream><ComponentStream component="Rotary" name="C" componentId="c1"><Samples><Angle dataItemId="Cact" timestamp="2025-07-03T10:31:11.291Z" name="Cact" sequence="44350">0</Angle><Load dataItemId="Cload" timestamp="2025-07-03T10:31:11.291Z" name="Cload" sequence="44351">0</Load></Samples></ComponentStream><ComponentStream component="Controller" name="controller" componentId="cn1"><Events><EmergencyStop dataItemId="estop" timestamp="2025-07-03T10:31:11.291Z" sequence="44345">ARMED</EmergencyStop></Events><Condition><Normal dataItemId="system" timestamp="2025-07-03T10:31:11.190Z" sequence="44336" type="SYSTEM"/></Condition></ComponentStream><ComponentStream component="Path" name="path" componentId="pth"><Samples><PathFeedrate dataItemId="fd1" timestamp="2025-07-03T05:52:15.722Z" name="feedrate" sequence="25">UNAVAILABLE</PathFeedrate><PathFeedrate dataItemId="fd2" timestamp="2025-07-03T10:31:11.291Z" name="Fovr" sequence="44338" subType="OVERRIDE">100</PathFeedrate><FeedrateOverride dataItemId="fd3" timestamp="2025-07-03T05:52:15.722Z" name="Rovr" sequence="27" subType="RAPID">UNAVAILABLE</FeedrateOverride></Samples><Events><Block dataItemId="block" timestamp="2025-07-03T11:45:22.146Z" name="block" sequence="57815">O0000%</Block><Execution dataItemId="execution" timestamp="2025-07-03T11:45:22.146Z" name="exec" sequence="57816">READY</Execution><Line dataItemId="line" timestamp="2025-07-03T11:24:37.331Z" name="line" sequence="54951">1111</Line><ControllerMode dataItemId="mode" timestamp="2025-07-03T11:45:11.441Z" name="mode" sequence="57777">MANUAL_DATA_INPUT</ControllerMode><PartCount dataItemId="part_count" timestamp="2025-07-03T11:26:34.224Z" name="part_count" sequence="55946">1989493</PartCount><Program dataItemId="program" timestamp="2025-07-03T11:45:22.146Z" name="program" sequence="57776">O0000</Program><ToolId dataItemId="tool_id" timestamp="2025-07-03T11:45:21.700Z" name="ToolId" sequence="57809">0</ToolId></Events></ComponentStream><ComponentStream component="Rotary" name="S0" componentId="s0"><Samples><SpindleSpeed dataItemId="SSovr" timestamp="2025-07-03T05:52:15.722Z" name="Sovr" sequence="11" subType="OVERRIDE">UNAVAILABLE</SpindleSpeed><SpindleSpeed dataItemId="Sspeed" timestamp="2025-07-03T05:52:15.722Z" name="Sspeed" sequence="13" subType="ACTUAL">UNAVAILABLE</SpindleSpeed><Load dataItemId="Sload" timestamp="2025-07-03T05:52:15.722Z" name="Sload" sequence="12" subType="ACTUAL">UNAVAILABLE</Load></Samples></ComponentStream><ComponentStream component="Rotary" name="S1" componentId="s1"><Samples><Load dataItemId="S1load" timestamp="2025-07-03T11:26:35.437Z" name="S1load" sequence="55962" subType="ACTUAL">0</Load><SpindleSpeed dataItemId="S1speed" timestamp="2025-07-03T11:26:35.033Z" name="S1speed" sequence="55958" subType="ACTUAL">0</SpindleSpeed></Samples></ComponentStream><ComponentStream component="Rotary" name="S2" componentId="s2"><Samples><Load dataItemId="S2load" timestamp="2025-07-03T05:52:15.722Z" name="S2load" sequence="9" subType="ACTUAL">UNAVAILABLE</Load><SpindleSpeed dataItemId="S2speed" timestamp="2025-07-03T05:52:15.722Z" name="S2speed" sequence="10" subType="ACTUAL">UNAVAILABLE</SpindleSpeed></Samples></ComponentStream><ComponentStream component="Linear" name="X" componentId="x1"><Samples><Position dataItemId="Xact" timestamp="2025-07-03T11:44:52.941Z" name="Xact" sequence="57733">368</Position><Load dataItemId="Xload" timestamp="2025-07-03T11:46:18.718Z" name="Xload" sequence="57929">33</Load></Samples></ComponentStream><ComponentStream component="Linear" name="Y" componentId="z1"><Samples><Position dataItemId="Yact" timestamp="2025-07-03T11:45:22.146Z" name="Yact" sequence="57819">-192.034</Position><Load dataItemId="Yload" timestamp="2025-07-03T11:46:20.979Z" name="Yload" sequence="57936">4</Load></Samples></ComponentStream><ComponentStream component="Linear" name="Z" componentId="z1"><Samples><Position dataItemId="Zact" timestamp="2025-07-03T11:45:21.700Z" name="Zact" sequence="57811">191.2</Position><Load dataItemId="Zload" timestamp="2025-07-03T11:46:21.399Z" name="Zload" sequence="57937">8</Load></Samples></ComponentStream></DeviceStream>
<DeviceStream name="XD-20" uuid="XD-20"><ComponentStream component="Device" name="XD-20" componentId=""><Events><AssetChanged dataItemId="_asset_chg" timestamp="2025-07-03T05:52:15.678Z" sequence="20" assetType="">UNAVAILABLE</AssetChanged><Availability dataItemId="avail" timestamp="2025-07-03T05:52:50.983Z" sequence="35">UNAVAILABLE</Availability></Events></ComponentStream><ComponentStream component="Rotary" name="A" componentId="a1"><Samples><Angle dataItemId="Aact" timestamp="2025-07-03T05:52:15.678Z" name="ALact" sequence="1">UNAVAILABLE</Angle><Load dataItemId="Aload" timestamp="2025-07-03T05:52:15.678Z" name="ALload" sequence="2">UNAVAILABLE</Load></Samples></ComponentStream><ComponentStream component="Rotary" name="B" componentId="b1"><Samples><Angle dataItemId="Bact" timestamp="2025-07-03T05:52:15.678Z" name="Bact" sequence="3">UNAVAILABLE</Angle><Load dataItemId="Bload" timestamp="2025-07-03T05:52:15.678Z" name="Bload" sequence="4">UNAVAILABLE</Load></Samples></ComponentStream><ComponentStream component="Rotary" name="C" componentId="c1"><Samples><Angle dataItemId="Cact" timestamp="2025-07-03T05:52:15.678Z" name="Cact" sequence="5">UNAVAILABLE</Angle><Load dataItemId="Cload" timestamp="2025-07-03T05:52:15.678Z" name="Cload" sequence="6">UNAVAILABLE</Load></Samples></ComponentStream><ComponentStream component="Controller" name="controller" componentId="cn1"><Events><EmergencyStop dataItemId="estop" timestamp="2025-07-03T05:52:15.678Z" sequence="23">UNAVAILABLE</EmergencyStop></Events><Condition><Unavailable dataItemId="system" timestamp="2025-07-03T05:52:15.678Z" sequence="32" type="SYSTEM"/></Condition></ComponentStream><ComponentStream component="Path" name="path" componentId="pth"><Samples><PathFeedrate dataItemId="fd1" timestamp="2025-07-03T05:52:15.678Z" name="feedrate" sequence="25">UNAVAILABLE</PathFeedrate><PathFeedrate dataItemId="fd2" timestamp="2025-07-03T05:52:15.678Z" name="Fovr" sequence="26" subType="OVERRIDE">UNAVAILABLE</PathFeedrate><FeedrateOverride dataItemId="fd3" timestamp="2025-07-03T05:52:15.678Z" name="Rovr" sequence="27" subType="RAPID">UNAVAILABLE</FeedrateOverride></Samples><Events><Block dataItemId="block" timestamp="2025-07-03T05:52:15.678Z" name="block" sequence="22">UNAVAILABLE</Block><Execution dataItemId="execution" timestamp="2025-07-03T05:52:15.678Z" name="exec" sequence="24">UNAVAILABLE</Execution><Line dataItemId="line" timestamp="2025-07-03T05:52:15.678Z" name="line" sequence="28">UNAVAILABLE</Line><ControllerMode dataItemId="mode" timestamp="2025-07-03T05:52:15.678Z" name="mode" sequence="29">UNAVAILABLE</ControllerMode><PartCount dataItemId="part_count" timestamp="2025-07-03T05:52:15.678Z" name="part_count" sequence="30">UNAVAILABLE</PartCount><Program dataItemId="program" timestamp="2025-07-03T05:52:15.678Z" name="program" sequence="31">UNAVAILABLE</Program><ToolId dataItemId="tool_id" timestamp="2025-07-03T05:52:15.678Z" name="ToolId" sequence="33">UNAVAILABLE</ToolId></Events></ComponentStream><ComponentStream component="Rotary" name="S0" componentId="s0"><Samples><SpindleSpeed dataItemId="SSovr" timestamp="2025-07-03T05:52:15.678Z" name="Sovr" sequence="11" subType="OVERRIDE">UNAVAILABLE</SpindleSpeed><SpindleSpeed dataItemId="Sspeed" timestamp="2025-07-03T05:52:15.678Z" name="Sspeed" sequence="13" subType="ACTUAL">UNAVAILABLE</SpindleSpeed><Load dataItemId="Sload" timestamp="2025-07-03T05:52:15.678Z" name="Sload" sequence="12" subType="ACTUAL">UNAVAILABLE</Load></Samples></ComponentStream><ComponentStream component="Rotary" name="S1" componentId="s1"><Samples><Load dataItemId="S1load" timestamp="2025-07-03T05:52:15.678Z" name="S1load" sequence="7" subType="ACTUAL">UNAVAILABLE</Load><SpindleSpeed dataItemId="S1speed" timestamp="2025-07-03T05:52:15.678Z" name="S1speed" sequence="8" subType="ACTUAL">UNAVAILABLE</SpindleSpeed></Samples></ComponentStream><ComponentStream component="Rotary" name="S2" componentId="s2"><Samples><Load dataItemId="S2load" timestamp="2025-07-03T05:52:15.678Z" name="S2load" sequence="9" subType="ACTUAL">UNAVAILABLE</Load><SpindleSpeed dataItemId="S2speed" timestamp="2025-07-03T05:52:15.678Z" name="S2speed" sequence="10" subType="ACTUAL">UNAVAILABLE</SpindleSpeed></Samples></ComponentStream><ComponentStream component="Linear" name="X" componentId="x1"><Samples><Position dataItemId="Xact" timestamp="2025-07-03T05:52:15.678Z" name="Xact" sequence="14">UNAVAILABLE</Position><Load dataItemId="Xload" timestamp="2025-07-03T05:52:15.678Z" name="Xload" sequence="15">UNAVAILABLE</Load></Samples></ComponentStream><ComponentStream component="Linear" name="Y" componentId="z1"><Samples><Position dataItemId="Yact" timestamp="2025-07-03T05:52:15.678Z" name="Yact" sequence="16">UNAVAILABLE</Position><Load dataItemId="Yload" timestamp="2025-07-03T05:52:15.678Z" name="Yload" sequence="17">UNAVAILABLE</Load></Samples></ComponentStream><ComponentStream component="Linear" name="Z" componentId="z1"><Samples><Position dataItemId="Zact" timestamp="2025-07-03T05:52:15.678Z" name="Zact" sequence="18">UNAVAILABLE</Position><Load dataItemId="Zload" timestamp="2025-07-03T05:52:15.678Z" name="Zload" sequence="19">UNAVAILABLE</Load></Samples></ComponentStream></DeviceStream>
<DeviceStream name="XD-38" uuid="XD-38"><ComponentStream component="Device" name="XD-38" componentId=""><Events><AssetChanged dataItemId="_asset_chg" timestamp="2025-07-03T05:52:15.803Z" sequence="20" assetType="">UNAVAILABLE</AssetChanged><Availability dataItemId="avail" timestamp="2025-07-03T05:52:15.856Z" sequence="34">AVAILABLE</Availability></Events></ComponentStream><ComponentStream component="Rotary" name="A" componentId="a1"><Samples><Angle dataItemId="Aact" timestamp="2025-07-03T05:52:15.803Z" name="ALact" sequence="1">UNAVAILABLE</Angle><Load dataItemId="Aload" timestamp="2025-07-03T05:52:15.803Z" name="ALload" sequence="2">UNAVAILABLE</Load></Samples></ComponentStream><ComponentStream component="Rotary" name="B" componentId="b1"><Samples><Angle dataItemId="Bact" timestamp="2025-07-03T05:52:15.803Z" name="Bact" sequence="3">UNAVAILABLE</Angle><Load dataItemId="Bload" timestamp="2025-07-03T05:52:15.803Z" name="Bload" sequence="4">UNAVAILABLE</Load></Samples></ComponentStream><ComponentStream component="Rotary" name="C" componentId="c1"><Samples><Angle dataItemId="Cact" timestamp="2025-07-03T05:52:15.803Z" name="Cact" sequence="5">UNAVAILABLE</Angle><Load dataItemId="Cload" timestamp="2025-07-03T05:52:15.803Z" name="Cload" sequence="6">UNAVAILABLE</Load></Samples></ComponentStream><ComponentStream component="Controller" name="controller" componentId="cn1"><Events><EmergencyStop dataItemId="estop" timestamp="2025-07-03T05:52:16.436Z" sequence="44">ARMED</EmergencyStop></Events><Condition><Normal dataItemId="system" timestamp="2025-07-03T05:52:15.856Z" sequence="35" type="SYSTEM"/></Condition></ComponentStream><ComponentStream component="Path" name="path" componentId="pth"><Samples><PathFeedrate dataItemId="fd1" timestamp="2025-07-03T05:52:15.803Z" name="feedrate" sequence="25">UNAVAILABLE</PathFeedrate><PathFeedrate dataItemId="fd2" timestamp="2025-07-03T05:52:16.436Z" name="Fovr" sequence="37" subType="OVERRIDE">100</PathFeedrate><FeedrateOverride dataItemId="fd3" timestamp="2025-07-03T05:52:15.803Z" name="Rovr" sequence="27" subType="RAPID">UNAVAILABLE</FeedrateOverride></Samples><Events><Block dataItemId="block" timestamp="2025-07-03T05:52:16.436Z" name="block" sequence="41">M96</Block><Execution dataItemId="execution" timestamp="2025-07-03T05:52:16.436Z" name="exec" sequence="43">STOPPED</Execution><Line dataItemId="line" timestamp="2025-07-03T05:52:16.436Z" name="line" sequence="40">1000</Line><ControllerMode dataItemId="mode" timestamp="2025-07-03T05:52:16.436Z" name="mode" sequence="42">AUTOMATIC</ControllerMode><PartCount dataItemId="part_count" timestamp="2025-07-03T05:52:16.436Z" name="part_count" sequence="36">1091</PartCount><Program dataItemId="program" timestamp="2025-07-03T05:52:16.436Z" name="program" sequence="39">24.24</Program><ToolId dataItemId="tool_id" timestamp="2025-07-03T05:52:16.436Z" name="ToolId" sequence="38">101</ToolId></Events></ComponentStream><ComponentStream component="Rotary" name="S0" componentId="s0"><Samples><SpindleSpeed dataItemId="SSovr" timestamp="2025-07-03T05:52:15.803Z" name="Sovr" sequence="11" subType="OVERRIDE">UNAVAILABLE</SpindleSpeed><SpindleSpeed dataItemId="Sspeed" timestamp="2025-07-03T05:52:15.803Z" name="Sspeed" sequence="13" subType="ACTUAL">UNAVAILABLE</SpindleSpeed><Load dataItemId="Sload" timestamp="2025-07-03T05:52:15.803Z" name="Sload" sequence="12" subType="ACTUAL">UNAVAILABLE</Load></Samples></ComponentStream><ComponentStream component="Rotary" name="S1" componentId="s1"><Samples><Load dataItemId="S1load" timestamp="2025-07-03T05:52:16.436Z" name="S1load" sequence="46" subType="ACTUAL">0</Load><SpindleSpeed dataItemId="S1speed" timestamp="2025-07-03T05:52:16.436Z" name="S1speed" sequence="45" subType="ACTUAL">0</SpindleSpeed></Samples></ComponentStream><ComponentStream component="Rotary" name="S2" componentId="s2"><Samples><Load dataItemId="S2load" timestamp="2025-07-03T05:52:15.803Z" name="S2load" sequence="9" subType="ACTUAL">UNAVAILABLE</Load><SpindleSpeed dataItemId="S2speed" timestamp="2025-07-03T05:52:15.803Z" name="S2speed" sequence="10" subType="ACTUAL">UNAVAILABLE</SpindleSpeed></Samples></ComponentStream><ComponentStream component="Linear" name="X" componentId="x1"><Samples><Position dataItemId="Xact" timestamp="2025-07-03T05:52:15.803Z" name="Xact" sequence="14">UNAVAILABLE</Position><Load dataItemId="Xload" timestamp="2025-07-03T05:52:15.803Z" name="Xload" sequence="15">UNAVAILABLE</Load></Samples></ComponentStream><ComponentStream component="Linear" name="Y" componentId="z1"><Samples><Position dataItemId="Yact" timestamp="2025-07-03T05:52:15.803Z" name="Yact" sequence="16">UNAVAILABLE</Position><Load dataItemId="Yload" timestamp="2025-07-03T05:52:15.803Z" name="Yload" sequence="17">UNAVAILABLE</Load></Samples></ComponentStream><ComponentStream component="Linear" name="Z" componentId="z1"><Samples><Position dataItemId="Zact" timestamp="2025-07-03T05:52:15.803Z" name="Zact" sequence="18">UNAVAILABLE</Position><Load dataItemId="Zload" timestamp="2025-07-03T05:52:15.803Z" name="Zload" sequence="19">UNAVAILABLE</Load></Samples></ComponentStream></DeviceStream>
    </Streams>

    <DeviceStream name="SR-22_Adam" uuid="adam-0">
      <ComponentStream component="Device" name="SR-22_Adam" componentId="adam_SR-22">
        <ComponentStream component="Controller" name="controller" componentId="adam_SR-22_controller">
          <ComponentStream component="Path" name="path" componentId="adam_SR-22_path">
            <Events>
              <PartCount dataItemId="adam_SR-22_part_count" timestamp="2025-07-03T11:46:23.003Z" name="PartCount" sequence="60391">58671</PartCount>
              <Execution dataItemId="adam_SR-22_execution" timestamp="2025-07-03T11:46:23.003Z" name="Execution" sequence="3867">ACTIVE</Execution>
            </Events>
            <Samples>
              
            </Samples>
          </ComponentStream>
        </ComponentStream>
      </ComponentStream>
    </DeviceStream>
    <DeviceStream name="SB-16_Adam" uuid="adam-1">
      <ComponentStream component="Device" name="SB-16_Adam" componentId="adam_SB-16">
        <ComponentStream component="Controller" name="controller" componentId="adam_SB-16_controller">
          <ComponentStream component="Path" name="path" componentId="adam_SB-16_path">
            <Events>
              <PartCount dataItemId="adam_SB-16_part_count" timestamp="2025-07-03T11:46:23.003Z" name="PartCount" sequence="14965">5</PartCount>
              <Execution dataItemId="adam_SB-16_execution" timestamp="2025-07-03T11:46:23.003Z" name="Execution" sequence="8346">ACTIVE</Execution>
            </Events>
            <Samples>
              
            </Samples>
          </ComponentStream>
        </ComponentStream>
      </ComponentStream>
    </DeviceStream>
    <DeviceStream name="BT-38_Adam" uuid="adam-2">
      <ComponentStream component="Device" name="BT-38_Adam" componentId="adam_BT-38">
        <ComponentStream component="Controller" name="controller" componentId="adam_BT-38_controller">
          <ComponentStream component="Path" name="path" componentId="adam_BT-38_path">
            <Events>
              <PartCount dataItemId="adam_BT-38_part_count" timestamp="2025-07-03T11:46:23.003Z" name="PartCount" sequence="39763">20395</PartCount>
              <Execution dataItemId="adam_BT-38_execution" timestamp="2025-07-03T11:46:23.003Z" name="Execution" sequence="58574">ACTIVE</Execution>
            </Events>
            <Samples>
              
            </Samples>
          </ComponentStream>
        </ComponentStream>
      </ComponentStream>
    </DeviceStream>
    <DeviceStream name="K-162_Adam" uuid="adam-3">
      <ComponentStream component="Device" name="K-162_Adam" componentId="adam_K-162">
        <ComponentStream component="Controller" name="controller" componentId="adam_K-162_controller">
          <ComponentStream component="Path" name="path" componentId="adam_K-162_path">
            <Events>
              <PartCount dataItemId="adam_K-162_part_count" timestamp="2025-07-03T11:46:23.003Z" name="PartCount" sequence="7524">8</PartCount>
              <Execution dataItemId="adam_K-162_execution" timestamp="2025-07-03T11:46:23.003Z" name="Execution" sequence="89106">ACTIVE</Execution>
            </Events>
            <Samples>
              
            </Samples>
          </ComponentStream>
        </ComponentStream>
      </ComponentStream>
    </DeviceStream>
    <DeviceStream name="K-163_Adam" uuid="adam-4">
      <ComponentStream component="Device" name="K-163_Adam" componentId="adam_K-163">
        <ComponentStream component="Controller" name="controller" componentId="adam_K-163_controller">
          <ComponentStream component="Path" name="path" componentId="adam_K-163_path">
            <Events>
              <PartCount dataItemId="adam_K-163_part_count" timestamp="2025-07-03T11:46:23.003Z" name="PartCount" sequence="99190">31261</PartCount>
              <Execution dataItemId="adam_K-163_execution" timestamp="2025-07-03T11:46:23.003Z" name="Execution" sequence="54717">ACTIVE</Execution>
            </Events>
            <Samples>
              
            </Samples>
          </ComponentStream>
        </ComponentStream>
      </ComponentStream>
    </DeviceStream>
    <DeviceStream name="L-20_Adam" uuid="adam-5">
      <ComponentStream component="Device" name="L-20_Adam" componentId="adam_L-20">
        <ComponentStream component="Controller" name="controller" componentId="adam_L-20_controller">
          <ComponentStream component="Path" name="path" componentId="adam_L-20_path">
            <Events>
              <PartCount dataItemId="adam_L-20_part_count" timestamp="2025-07-03T11:46:23.003Z" name="PartCount" sequence="81678">2</PartCount>
              <Execution dataItemId="adam_L-20_execution" timestamp="2025-07-03T11:46:23.003Z" name="Execution" sequence="96788">ACTIVE</Execution>
            </Events>
            <Samples>
              
            </Samples>
          </ComponentStream>
        </ComponentStream>
      </ComponentStream>
    </DeviceStream>
    <DeviceStream name="K-16_Adam" uuid="adam-6">
      <ComponentStream component="Device" name="K-16_Adam" componentId="adam_K-16">
        <ComponentStream component="Controller" name="controller" componentId="adam_K-16_controller">
          <ComponentStream component="Path" name="path" componentId="adam_K-16_path">
            <Events>
              <PartCount dataItemId="adam_K-16_part_count" timestamp="2025-07-03T11:46:23.003Z" name="PartCount" sequence="54156">57589</PartCount>
              <Execution dataItemId="adam_K-16_execution" timestamp="2025-07-03T11:46:23.003Z" name="Execution" sequence="61795">ACTIVE</Execution>
            </Events>
            <Samples>
              
            </Samples>
          </ComponentStream>
        </ComponentStream>
      </ComponentStream>
    </DeviceStream>
    <DeviceStream name="SR-20_Adam" uuid="adam-8">
      <ComponentStream component="Device" name="SR-20_Adam" componentId="adam_SR-20">
        <ComponentStream component="Controller" name="controller" componentId="adam_SR-20_controller">
          <ComponentStream component="Path" name="path" componentId="adam_SR-20_path">
            <Events>
              <PartCount dataItemId="adam_SR-20_part_count" timestamp="2025-07-03T11:46:23.003Z" name="PartCount" sequence="29849">43743</PartCount>
              <Execution dataItemId="adam_SR-20_execution" timestamp="2025-07-03T11:46:23.003Z" name="Execution" sequence="62665">ACTIVE</Execution>
            </Events>
            <Samples>
              
            </Samples>
          </ComponentStream>
        </ComponentStream>
      </ComponentStream>
    </DeviceStream>
    <DeviceStream name="SR-32_Adam" uuid="adam-9">
      <ComponentStream component="Device" name="SR-32_Adam" componentId="adam_SR-32">
        <ComponentStream component="Controller" name="controller" componentId="adam_SR-32_controller">
          <ComponentStream component="Path" name="path" componentId="adam_SR-32_path">
            <Events>
              <PartCount dataItemId="adam_SR-32_part_count" timestamp="2025-07-03T11:46:23.003Z" name="PartCount" sequence="46285">5</PartCount>
              <Execution dataItemId="adam_SR-32_execution" timestamp="2025-07-03T11:46:23.003Z" name="Execution" sequence="6173">ACTIVE</Execution>
            </Events>
            <Samples>
              
            </Samples>
          </ComponentStream>
        </ComponentStream>
      </ComponentStream>
    </DeviceStream>
    <DeviceStream name="SR-24_Adam" uuid="adam-10">
      <ComponentStream component="Device" name="SR-24_Adam" componentId="adam_SR-24">
        <ComponentStream component="Controller" name="controller" componentId="adam_SR-24_controller">
          <ComponentStream component="Path" name="path" componentId="adam_SR-24_path">
            <Events>
              <PartCount dataItemId="adam_SR-24_part_count" timestamp="2025-07-03T11:46:23.003Z" name="PartCount" sequence="94694">35589</PartCount>
              <Execution dataItemId="adam_SR-24_execution" timestamp="2025-07-03T11:46:23.003Z" name="Execution" sequence="70624">ACTIVE</Execution>
            </Events>
            <Samples>
              <ProcessTimer dataItemId="adam_SR-24_cycle_time" timestamp="2025-07-03T11:46:23.003Z" name="CycleTime" sequence="68467" subType="AVERAGE" type="PROCESS_TIMER">5.14</ProcessTimer>
            </Samples>
          </ComponentStream>
        </ComponentStream>
      </ComponentStream>
    </DeviceStream>
  </MTConnectStreams>